nshare_calc/__init__.py
nshare_calc/nshare_calc.py
nshare_calc-0.1.2.dist-info/LICENSE
nshare_calc-0.1.2.dist-info/METADATA
nshare_calc-0.1.2.dist-info/WHEEL
nshare_calc-0.1.2.dist-info/top_level.txt
nshare_calc-0.1.2.dist-info/RECORD
