Metadata-Version: 2.1
Name: nshare-calc
Version: 0.1.2
Summary: Python library for calculating the optimal number of shares given a portfolio using integer programming.
Author-email: Yfiua <yfiua6@gmail.com>
Project-URL: Homepage, https://github.com/yfiua/nshare-calc
Project-URL: Bug Tracker, https://github.com/yfiua/nshare-calc/issues
Classifier: Programming Language :: Python :: 3
Classifier: License :: OSI Approved :: Apache Software License
Classifier: Operating System :: OS Independent
Requires-Python: >=3.7
License-File: LICENSE
Requires-Dist: numpy (>=1.24.1)
Requires-Dist: pulp (>=2.7.0)
